pagey/__init__.py
pagey/args.py
pagey/defaults.py
pagey/pagerduty/__init__.py
pagey/slack/__init__.py
pagey-0.2.0.dist-info/LICENSE.txt
pagey-0.2.0.dist-info/METADATA
pagey-0.2.0.dist-info/WHEEL
pagey-0.2.0.dist-info/entry_points.txt
pagey-0.2.0.dist-info/top_level.txt
pagey-0.2.0.dist-info/RECORD
