Metadata-Version: 2.1
Name: pagey
Version: 0.2.0
Summary: Pagey is a Pagerduty slack bot.
Home-page: https://github.com/Flaconi/slackbot-pagey
Author: cytopia
Author-email: cytopia@everythingcli.org
License: MIT
Project-URL: Source Code, https://github.com/Flaconi/slackbot-pagey
Project-URL: Bug Tracker, https://github.com/Flaconi/slackbot-pagey
Keywords: pagerduty,slack
Classifier: Development Status :: 3 - Alpha
Classifier: Environment :: Console
Classifier: Intended Audience :: Developers
Classifier: Intended Audience :: Information Technology
Classifier: Intended Audience :: System Administrators
Classifier: License :: OSI Approved :: MIT License
Classifier: Operating System :: OS Independent
Classifier: Programming Language :: Python :: 3 :: Only
Classifier: Programming Language :: Python :: 3.8
Classifier: Programming Language :: Python :: 3.9
Classifier: Programming Language :: Python :: 3.10
Classifier: Programming Language :: Python :: 3.11
Classifier: Programming Language :: Python :: 3.12
Classifier: Programming Language :: Python :: Implementation :: CPython
Classifier: Programming Language :: Python :: Implementation :: PyPy
Classifier: Topic :: Internet
Classifier: Topic :: Security
Classifier: Topic :: System :: Systems Administration
Classifier: Topic :: Utilities
Classifier: Typing :: Typed
Requires-Python: >=3.8
License-File: LICENSE.txt
Requires-Dist: python-dateutil
Requires-Dist: requests
Requires-Dist: slackclient ==1.3.2
